aioserver/__init__.py
aioserver/aioserver.py
aioserver/middleware.py
aioserver-0.7.4.dist-info/licenses/LICENSE.md
aioserver-0.7.4.dist-info/METADATA
aioserver-0.7.4.dist-info/WHEEL
aioserver-0.7.4.dist-info/top_level.txt
aioserver-0.7.4.dist-info/RECORD
